lb_controller/__init__.py
lb_controller/cli_parse.py
lb_controller/daemon.py
lb_controller/event_handler.py
lb_controller/k8s_cache.py
lb_controller/main.py
lb_controller-0.0.9.dist-info/METADATA
lb_controller-0.0.9.dist-info/WHEEL
lb_controller-0.0.9.dist-info/top_level.txt
lb_controller-0.0.9.dist-info/RECORD
