Metadata-Version: 2.1
Name: lb-controller
Version: 0.0.9
Summary: A controller to auto configure k8s load balancer on premise
Home-page: UNKNOWN
License: UNKNOWN
Platform: UNKNOWN
Classifier: Programming Language :: Python :: 3
Classifier: License :: OSI Approved :: MIT License
Classifier: Operating System :: OS Independent
Requires-Dist: kubernetes (==10.0.1)
Requires-Dist: kubernetes-asyncio (==10.0.0)
Requires-Dist: jinja2 (==2.10.3)
Requires-Dist: multidict (==4.6.1)
Requires-Dist: aiohttp (==3.6.1)
Requires-Dist: prometheus-client (==0.7.1)
Provides-Extra: tests
Requires-Dist: pytest (==4.6.3) ; extra == 'tests'
